{"preview":[{"views":[{"id":"codesandbox.browser"},{"id":"codesandbox.browser","closeable":true,"options":{"url":"/___graphql","title":"GraphiQL"}},{"id":"codesandbox.browser","options":{"port":44289,"url":"https://zz5vn-44289.sse.codesandbox.io"},"closeable":true},{"id":"codesandbox.browser","options":{"port":43215,"url":"https://zz5vn-43215.sse.codesandbox.io"},"closeable":true}]},{"open":true,"views":[{"id":"codesandbox.terminal"},{"id":"codesandbox.console"},{"id":"codesandbox.problems"}]}]}